{
"type": "FeatureCollection",
"name": "droguerías_pois",
"crs": { "type": "name", "properties": { "name": "urn:ogc:def:crs:OGC:1.3:CRS84" } },
"features": [
{ "type": "Feature", "properties": { }, "geometry": { "type": "Point", "coordinates": [ -74.0913215, 4.7499086 ] } },
{ "type": "Feature", "properties": { }, "geometry": { "type": "Point", "coordinates": [ -74.100548, 4.7538346 ] } },
{ "type": "Feature", "properties": { }, "geometry": { "type": "Point", "coordinates": [ -74.0986407, 4.7478533 ] } },
{ "type": "Feature", "properties": { }, "geometry": { "type": "Point", "coordinates": [ -74.0921213, 4.7483909 ] } },
{ "type": "Feature", "properties": { }, "geometry": { "type": "Point", "coordinates": [ -74.0896779, 4.7510982 ] } }
]
}
